<formalpara xmlns="http://docbook.org/ns/docbook" xmlns:xi="http://www.w3.org/2001/XInclude" version="5.0">
	<title>38</title>
	<para>
		Die Anschauung bei roddoro ist: etwas in einem gewissen Zustande empfangen oder finden und es in einem veränderten Zustande gleichsam zurückgeben; reddere legt demnach den Hauptnachdruck aus die eingetretene Veränderung (- „ umgestalten«); dabei ist aber durchaus nicht nötig. daß jemand die Herbeiführung des neuen Zustandes beabsichtigt hat. Faeere heißt gewöhnlich schlechtweg „machen“; zuweilen stellt es aber auch die Wirkung als beabsichtigt hin, als nach oorhergehender Entschließung herbeigeführt (- efficere «geftalten«, cf. 3, Anm. 1). Daraus ergiebt sich, daß die Süße: »Gott hat den Leib des Menschen aufrecht gemacht; die Natur hat den Mann liihner gemacht als das Weib; die Griechen machten bisweilen den Monat um einen oder zwei Tage länger" das Verbum reddere durchaus nicht zulassen, während Säfte wie: .Themistolles machte die Athener im Kriegswesen erfahren; das Glück macht die Menschen oft blind; Pompejus machte alle Meere vor den Seeräubern sicher« ebensowohl reddcre als facere gestatten.
		<note>
			<title>Anm. 1.</title>
			<para>
				Es heißt stets eeytiaisem facere (aliqnem alicuius rei od. de re). Ebenso sagt man nur reum facere aliquem „einen zum Beilagten machen, anklagen« und plammr facere aliquid »etwas beweisen«. — »Ein Land zur (r’omischen) Provinz machen" terram in provian oder in provinciac sama-n redigere.
			</para>
		</note>
		<note>
			<title>Anm. 2.</title>
			<para>
				»Gemacht werden« heißt bei guten Schriftstellern nicht reddt', sondern stets fien' oder qfici (cf. jedoch Cic. inv. l, 95). Daher muß in dem»leßten der vorgelegten Sätze statt redditi sunt notwendig facti auut geschrieben werden. —- Uber facere es: »jemanden aus etwas zu etwas anderem machen« cf. 3, Anm. 2.
			</para>
		</note>
	</para>
</formalpara>
