<formalpara xmlns="http://docbook.org/ns/docbook" xmlns:xi="http://www.w3.org/2001/XInclude" version="5.0">
	<title>38</title>
	<para>
		Welcher Unterschied entsteht, jenachdem man bei der Übersetzung der Ausdrücke <quote>Jemanden besser (glücklich, reich <foreignphrase>sc</foreignphrase><!-- FIXME: sc? etc? -->.) machen, die Menschen aus wilden zu sanften machen, eine Gegend vor dem Feinde sicher machen</quote> das Verbum <foreignphrase>facere</foreignphrase> oder <foreignphrase>reddere</foreignphrase> anwendet? Ist der Satz: <quote>Die Menschen sollen von Orpheus aus wilden zu sanften gemacht sein</quote> richtig übersetzt <foreignphrase>Homines ab Orpheo ex agrestibus mites <emphasis>redditi</emphasis> esse dicuntur</foreignphrase>?
	</para>
</formalpara>